{"version":1,"resource":"file:///home/su/Documents/aa/multi_tenant/templates/projects.html","entries":[{"id":"nJKA.html","timestamp":1766148280419},{"id":"Bm9B.html","timestamp":1766148524011},{"id":"53K7.html","timestamp":1766148694701},{"id":"b0dw.html","timestamp":1766149733489},{"id":"6ZYQ.html","timestamp":1766149904790},{"id":"dezg.html","timestamp":1766150176295},{"id":"YLFb.html","timestamp":1766150361861},{"id":"Tpdu.html","timestamp":1766150393290},{"id":"1KJO.html","timestamp":1766150574719},{"id":"mxBe.html","timestamp":1766150594259},{"id":"sqdB.html","timestamp":1766150641088},{"id":"DIUa.html","timestamp":1766150735792},{"id":"PyhZ.html","timestamp":1766150784768},{"id":"21ME.html","timestamp":1766151062182}]}